macpyver_cisco_source/__init__.py
macpyver_cisco_source/cisco_source.py
macpyver_cisco_source/exceptions.py
macpyver_cisco_source/py.typed
macpyver_cisco_source-1.0.1.dist-info/LICENSE.md
macpyver_cisco_source-1.0.1.dist-info/METADATA
macpyver_cisco_source-1.0.1.dist-info/WHEEL
macpyver_cisco_source-1.0.1.dist-info/RECORD
